{
  "book_code": "3JN",
  "position": 74,
  "testament": "NT",
  "status": "complete",
  "content_surface": "study",
  "verification_surface": "staging",
  "footnotes_path": "/home/ark/orthodoxphronema/study/footnotes/NT/3JN_footnotes.md",
  "component_status": {
    "mechanical_clean": true,
    "structural_clean": true,
    "marker_alignment_pass": true,
    "wikilinks_verified": true,
    "patristic_entity_verified": true,
    "apostolic_entity_verified": true,
    "liturgical_creedal_verified": true
  },
  "mechanical": {
    "tool_status": "ok",
    "summary": {
      "total_findings": 10,
      "auto_fixable": 0,
      "review_needed": 10,
      "files_checked": 1,
      "lines_checked": 24,
      "lines_fixed": 0
    },
    "by_category": {
      "P6": 10
    }
  },
  "structure": {
    "issue_count": 0,
    "findings": [],
    "truncated": false
  },
  "footnote_verification": {
    "book_code": "3JN",
    "testament": "NT",
    "status": "pass",
    "markers_path": "/home/ark/orthodoxphronema/staging/validated/NT/3JN_footnote_markers.json",
    "notes_path": "/home/ark/orthodoxphronema/staging/validated/NT/3JN_footnotes.md",
    "scripture_path": "/home/ark/orthodoxphronema/staging/validated/NT/3JN.md",
    "counts": {
      "scripture_markers": 6,
      "footnote_entries": 6,
      "scripture_anchors": 15,
      "valid_marker_anchors": 6,
      "valid_note_anchors": 6
    },
    "invalid_marker_anchors": {},
    "invalid_note_anchors": {},
    "missing_in_notes": [],
    "missing_in_scripture": [],
    "marker_anchor_gaps": [],
    "note_anchor_gaps": [],
    "issue_count": 0
  },
  "wikilinks": {
    "total_refs": 4,
    "convertible_refs": 0,
    "already_linked_refs": 4,
    "unresolved_refs": 0,
    "unresolved_examples": []
  },
  "source_entities": {
    "patristic": {
      "matched_entities_count": 0,
      "matched_entities": [],
      "entity_counts": {},
      "unresolved_candidates_count": 0,
      "unresolved_candidates": [],
      "explicit_citation_snippets": []
    },
    "apostolic": {
      "matched_entities_count": 0,
      "matched_entities": [],
      "entity_counts": {},
      "unresolved_candidates_count": 0,
      "unresolved_candidates": [],
      "explicit_citation_snippets": []
    },
    "liturgical_creedal": {
      "matched_entities_count": 0,
      "matched_entities": [],
      "entity_counts": {},
      "unresolved_candidates_count": 0,
      "unresolved_candidates": [],
      "explicit_citation_snippets": []
    }
  },
  "patristics": {
    "matched_entities_count": 0,
    "matched_entities": [],
    "entity_counts": {},
    "unresolved_candidates_count": 0,
    "unresolved_candidates": [],
    "explicit_citation_snippets": []
  }
}
