{
  "anchor_id": "ACT.13:1",
  "canon_uri": "canon/NT/ACT.md#ACT.13:1",
  "text_tradition": "LXX",
  "generated_at": "2026-03-13T21:28:41+00:00",
  "generator_version": "phase3-backlinks-v1",
  "links": [
    {
      "source_file": "staging/validated/NT/MAT_footnotes.md",
      "line_number": 3181,
      "raw_match": "[[ACT.13:1]]",
      "reference_type": "wikilink",
      "context": "[[ACT.13:1]]; [[1CO.12:28]]; [[EPH.4:11]]; and [[2TI.1:11]]. Father is used in [[LUK.16:24]]; [[1CO.4:15]]; and Col"
    }
  ]
}
