{
  "anchor_id": "EPH.6:1",
  "canon_uri": "canon/NT/EPH.md#EPH.6:1",
  "text_tradition": "LXX",
  "generated_at": "2026-03-16T02:01:16+00:00",
  "generator_version": "phase3-backlinks-v1",
  "schema_version": "v2",
  "verse_text": "Children, obey your parents in the Lord, for this is right.",
  "pericope": {
    "id": "EPH.P016",
    "title": "Children and Parents",
    "range": "EPH.5:33-6:3",
    "liturgical_use": []
  },
  "topic_threads": [],
  "depth_available": 3,
  "links": [
    {
      "source_file": "study/footnotes/OT/EXO_footnotes.md",
      "line_number": 784,
      "raw_match": "[[EPH.6:1]]",
      "reference_type": "wikilink",
      "context": "God offers no rewards in the prohibitions of the Ten Commandments. God's promise of reward is offered to those who keep the positive ones. For example, to honor one's father and mother is the first commandment in the Ten to promise a reward, namely, a long and spiritually prosperous life on earth ([[EPH.6:1]], [[EPH.6:2]]; JohnChr)."
    }
  ]
}
