{
  "anchor_id": "GEN.3:16",
  "canon_uri": "canon/OT/GEN.md#GEN.3:16",
  "text_tradition": "LXX",
  "generated_at": "2026-03-13T21:28:41+00:00",
  "generator_version": "phase3-backlinks-v1",
  "links": [
    {
      "source_file": "staging/validated/NT/REV_footnotes.md",
      "line_number": 3071,
      "raw_match": "[[GEN.3:16]]-19",
      "reference_type": "wikilink_range",
      "context": "Holy City: a reversal of the curse of [[GEN.3:16]]-19. The fruits and leaves of the tree are"
    }
  ]
}
