{
  "anchor_id": "LUK.5:13",
  "canon_uri": "canon/NT/LUK.md#LUK.5:13",
  "text_tradition": "LXX",
  "generated_at": "2026-03-16T02:01:16+00:00",
  "generator_version": "phase3-backlinks-v1",
  "schema_version": "v3",
  "verse_text": "Then He put out His hand and touched him, saying, 'I am willing; be cleansed.' Immediately the leprosy left him.",
  "pericope": {
    "id": "LUK.P023",
    "title": "Four Fishermen Called",
    "range": "LUK.4:44-5:15",
    "liturgical_use": []
  },
  "topic_threads": [],
  "depth_available": 3,
  "links": [
    {
      "source_file": "study/footnotes/NT/MRK_footnotes.md",
      "line_number": 53,
      "raw_match": "[[LUK.5:12]]-16",
      "reference_type": "wikilink_range",
      "context": "On the cleansing of the leper, see notes at [[MAT.8:1]]-4 and [[LUK.5:12]]-16.",
      "edge_type": "instantiates",
      "symbolic": {
        "source": "pageau",
        "chapter": 3,
        "title": "Returning to the Garden of Eden",
        "polarity": "light",
        "operation": "inform",
        "scale": "cosmic"
      }
    }
  ]
}
