{
  "anchor_id": "MAT.27:29",
  "canon_uri": "canon/NT/MAT.md#MAT.27:29",
  "text_tradition": "LXX",
  "generated_at": "2026-03-13T21:28:41+00:00",
  "generator_version": "phase3-backlinks-v1",
  "links": [
    {
      "source_file": "staging/validated/NT/JOH_footnotes.md",
      "line_number": 3091,
      "raw_match": "[[MAT.27:27]]-31",
      "reference_type": "wikilink_range",
      "context": "at [[MAT.27:27]]-31). Scourging was a severe punishment using a whip that had bits of bone or"
    },
    {
      "source_file": "staging/validated/OT/1CH_footnotes.md",
      "line_number": 267,
      "raw_match": "[[MAT.27:27]]-35",
      "reference_type": "wikilink_range",
      "context": "mocked Him, stripped Him, and divided His garments ([[MAT.27:27]]-35), but also the"
    },
    {
      "source_file": "staging/validated/OT/1CH_footnotes.md",
      "line_number": 275,
      "raw_match": "[[MAT.27:29]]",
      "reference_type": "wikilink",
      "context": "crown of thorns ([[MAT.27:29]]), given by those to whom He extended divine kindness. 20:4-8 The lesson that God \"exalts the humble with salvation\" ([[PSA.149:4]]) continues when"
    },
    {
      "source_file": "staging/validated/OT/JOB_footnotes.md",
      "line_number": 373,
      "raw_match": "[[MAT.27:29]]",
      "reference_type": "wikilink",
      "context": "; [[JOH.18:23]]; [[MAT.27:26]], [[MAT.27:27]], [[MAT.27:29]]; Is 53:2, 3). 19:23-27 \"No one since the days of Christ speaks so openly concerning the Resurrection as"
    }
  ]
}
