{
  "anchor_id": "MAT.9:37",
  "canon_uri": "canon/NT/MAT.md#MAT.9:37",
  "text_tradition": "LXX",
  "generated_at": "2026-03-13T21:28:41+00:00",
  "generator_version": "phase3-backlinks-v1",
  "links": [
    {
      "source_file": "staging/validated/OT/RUT_footnotes.md",
      "line_number": 86,
      "raw_match": "[[MAT.9:37]]",
      "reference_type": "wikilink",
      "context": "Himself refers to the new covenant as a time of harvest ([[MAT.9:37]], [[MAT.9:38]]; [[JOH.4:35]]). Ruth is"
    }
  ]
}
