{
  "anchor_id": "MRK.14:7",
  "canon_uri": "canon/NT/MRK.md#MRK.14:7",
  "text_tradition": "LXX",
  "generated_at": "2026-03-16T02:01:16+00:00",
  "generator_version": "phase3-backlinks-v1",
  "schema_version": "v2",
  "verse_text": "For you have the poor with you always, and whenever you wish you may do them good; but Me you do not have always.",
  "pericope": {
    "id": "MRK.P049",
    "title": "The Anointing at Bethany",
    "range": "MRK.14:2-14:8",
    "liturgical_use": []
  },
  "topic_threads": [],
  "depth_available": 3,
  "links": [
    {
      "source_file": "study/footnotes/NT/MAT_footnotes.md",
      "line_number": 2301,
      "raw_match": "[[MRK.14:3]]-9",
      "reference_type": "wikilink_range",
      "context": "Because of her fervent faith, Jesus promises perpetual public memory of this woman. There is no consensus among the Fathers as to her identity in relation to accounts of similar events in [[MRK.14:3]]-9; [[LUK.7:36]]-38; and [[JOH.12:1]]-8. Some Fathers say that there were three different women in these four accounts, others that there were only two."
    }
  ]
}
