{
  "anchor_id": "MRK.13:27",
  "canon_uri": "canon/NT/MRK.md#MRK.13:27",
  "text_tradition": "LXX",
  "generated_at": "2026-03-13T21:28:41+00:00",
  "generator_version": "phase3-backlinks-v1",
  "links": [
    {
      "source_file": "staging/validated/NT/REV_footnotes.md",
      "line_number": 1143,
      "raw_match": "[[MRK.13:27]]",
      "reference_type": "wikilink",
      "context": "literature ([[JER.25:16]]; [[ZEC.2:10]]; [[DAN.8:8]]; [[MRK.13:27]]; see also 1En 76:1-4). They are"
    },
    {
      "source_file": "staging/validated/OT/ZEC_footnotes.md",
      "line_number": 663,
      "raw_match": "[[MRK.13:7]]-27",
      "reference_type": "wikilink_range",
      "context": "delivery of His people, and the establishment of a secure, peaceful land (see Is 66:15-23; Ezk 38-40; Joel 4:9-21; [[MRK.13:7]]-27; Rev 20-22). In the New Testament, this is to be"
    }
  ]
}
